{
    "mod": "Net Pozer Jacket and Cyberdeck Armband",
    "url": "https://www.nexusmods.com/cyberpunk2077/mods/18715",
    "atelier": "https://www.nexusmods.com/cyberpunk2077/mods/18044",
    "atelierName": "Corpo Clothing",
    "authors": [
        "Sumi",
        "SumiTerra"
    ],
    "tags": [
        "Body-Gymfiend",
        "Body-Hyst-Angel",
        "Body-Hyst-EBB",
        "Body-Hyst-EBBP",
        "Body-Vanilla",
        "Clothing",
        "FemV",
        "GarmentSupport",
        "MaleV"
    ],
    "itemCategories": [
        {
            "label": "Cyberdeck Armband, Large",
            "tags": [
                "Accessories",
                "Arms"
            ],
            "items": [
                {
                    "name": "Blue",
                    "code": "sumi_cyberdeck_armband_lg_blue"
                },
                {
                    "name": "Green",
                    "code": "sumi_cyberdeck_armband_lg_green"
                },
                {
                    "name": "Pink",
                    "code": "sumi_cyberdeck_armband_lg_pink"
                },
                {
                    "name": "Purple",
                    "code": "sumi_cyberdeck_armband_lg_purple"
                },
                {
                    "name": "Red",
                    "code": "sumi_cyberdeck_armband_lg_red"
                },
                {
                    "name": "Yellow",
                    "code": "sumi_cyberdeck_armband_lg_yellow"
                }
            ]
        },
        {
            "label": "Cyberdeck Armband, Small",
            "tags": [
                "Accessories",
                "Arms"
            ],
            "items": [
                {
                    "name": "Blue",
                    "code": "sumi_cyberdeck_armband_lg_blue"
                },
                {
                    "name": "Green",
                    "code": "sumi_cyberdeck_armband_lg_green"
                },
                {
                    "name": "Pink",
                    "code": "sumi_cyberdeck_armband_lg_pink"
                },
                {
                    "name": "Purple",
                    "code": "sumi_cyberdeck_armband_lg_purple"
                },
                {
                    "name": "Red",
                    "code": "sumi_cyberdeck_armband_lg_red"
                },
                {
                    "name": "Yellow",
                    "code": "sumi_cyberdeck_armband_lg_yellow"
                }
            ]
        },
        {
            "label": "Decals",
            "tags": [
                "Accessories",
                "Decals",
                "Torso"
            ],
            "items": [
                {
                    "name": "Aldecaldos",
                    "code": "sumi_netpozer_decal_aldecaldos"
                },
                {
                    "name": "Arasaka",
                    "code": "sumi_netpozer_decal_arasaka"
                },
                {
                    "name": "Barghest Green",
                    "code": "sumi_netpozer_decal_barghestgreen"
                },
                {
                    "name": "Barghest White",
                    "code": "sumi_netpozer_decal_barghestwhite"
                },
                {
                    "name": "MaxTac",
                    "code": "sumi_netpozer_decal_maxtac"
                },
                {
                    "name": "Militech",
                    "code": "sumi_netpozer_decal_militech"
                },
                {
                    "name": "Mox",
                    "code": "sumi_netpozer_decal_mox"
                },
                {
                    "name": "Netwatch",
                    "code": "sumi_netpozer_decal_netwatch"
                },
                {
                    "name": "Night City Heat",
                    "code": "sumi_netpozer_decal_nightcityheat"
                },
                {
                    "name": "Predator",
                    "code": "sumi_netpozer_decal_predator"
                },
                {
                    "name": "Samurai",
                    "code": "sumi_netpozer_decal_samurai"
                },
                {
                    "name": "Samurai Wolf",
                    "code": "sumi_netpozer_decal_samuraiwolf"
                },
                {
                    "name": "Second Conflict",
                    "code": "sumi_netpozer_decal_secondconflict"
                },
                {
                    "name": "Trauma",
                    "code": "sumi_netpozer_decal_trauma"
                },
                {
                    "name": "Tyger",
                    "code": "sumi_netpozer_decal_tyger"
                },
                {
                    "name": "Valentinos",
                    "code": "sumi_netpozer_decal_valentinos"
                },
                {
                    "name": "Wolf",
                    "code": "sumi_netpozer_decal_wolf"
                },
                {
                    "name": "Wraith",
                    "code": "sumi_netpozer_decal_wraith"
                }
            ]
        },
        {
            "label": "Jacket, Long Sleeves",
            "tags": [
                "Jacket",
                "Torso"
            ],
            "items": [
                {
                    "name": "Netwatch Blue",
                    "code": "sumi_net_pozer_jacket_long_netwatch_blue"
                },
                {
                    "name": "Netwatch Green",
                    "code": "sumi_net_pozer_jacket_long_netwatch_green"
                },
                {
                    "name": "Netwatch Pink",
                    "code": "sumi_net_pozer_jacket_long_netwatch_pink"
                },
                {
                    "name": "Netwatch Purple",
                    "code": "sumi_net_pozer_jacket_long_netwatch_purple"
                },
                {
                    "name": "Netwatch Red",
                    "code": "sumi_net_pozer_jacket_long_netwatch_red"
                },
                {
                    "name": "Netwatch Yellow",
                    "code": "sumi_net_pozer_jacket_long_netwatch_yellow"
                },
                {
                    "name": "None Blue",
                    "code": "sumi_net_pozer_jacket_long_none_blue"
                },
                {
                    "name": "None Green",
                    "code": "sumi_net_pozer_jacket_long_none_green"
                },
                {
                    "name": "None Pink",
                    "code": "sumi_net_pozer_jacket_long_none_pink"
                },
                {
                    "name": "None Purple",
                    "code": "sumi_net_pozer_jacket_long_none_purple"
                },
                {
                    "name": "None Red",
                    "code": "sumi_net_pozer_jacket_long_none_red"
                },
                {
                    "name": "None Yellow",
                    "code": "sumi_net_pozer_jacket_long_none_yellow"
                },
                {
                    "name": "Samurai Blue",
                    "code": "sumi_net_pozer_jacket_long_samurai_blue"
                },
                {
                    "name": "Samurai Green",
                    "code": "sumi_net_pozer_jacket_long_samurai_green"
                },
                {
                    "name": "Samurai Pink",
                    "code": "sumi_net_pozer_jacket_long_samurai_pink"
                },
                {
                    "name": "Samurai Purple",
                    "code": "sumi_net_pozer_jacket_long_samurai_purple"
                },
                {
                    "name": "Samurai Red",
                    "code": "sumi_net_pozer_jacket_long_samurai_red"
                },
                {
                    "name": "Samurai Yellow",
                    "code": "sumi_net_pozer_jacket_long_samurai_yellow"
                },
                {
                    "name": "Wolf Blue",
                    "code": "sumi_net_pozer_jacket_long_wolf_blue"
                },
                {
                    "name": "Wolf Green",
                    "code": "sumi_net_pozer_jacket_long_wolf_green"
                },
                {
                    "name": "Wolf Pink",
                    "code": "sumi_net_pozer_jacket_long_wolf_pink"
                },
                {
                    "name": "Wolf Purple",
                    "code": "sumi_net_pozer_jacket_long_wolf_purple"
                },
                {
                    "name": "Wolf Red",
                    "code": "sumi_net_pozer_jacket_long_wolf_red"
                },
                {
                    "name": "Wolf Yellow",
                    "code": "sumi_net_pozer_jacket_long_wolf_yellow"
                }
            ]
        },
        {
            "label": "Jacket, Rolled Sleeves",
            "tags": [
                "Jacket",
                "Torso"
            ],
            "items": [
                {
                    "name": "Netwatch Blue",
                    "code": "sumi_net_pozer_jacket_netwatch_blue"
                },
                {
                    "name": "Netwatch Green",
                    "code": "sumi_net_pozer_jacket_netwatch_green"
                },
                {
                    "name": "Netwatch Pink",
                    "code": "sumi_net_pozer_jacket_netwatch_pink"
                },
                {
                    "name": "Netwatch Purple",
                    "code": "sumi_net_pozer_jacket_netwatch_purple"
                },
                {
                    "name": "Netwatch Red",
                    "code": "sumi_net_pozer_jacket_netwatch_red"
                },
                {
                    "name": "Netwatch Yellow",
                    "code": "sumi_net_pozer_jacket_netwatch_yellow"
                },
                {
                    "name": "None Blue",
                    "code": "sumi_net_pozer_jacket_none_blue"
                },
                {
                    "name": "None Green",
                    "code": "sumi_net_pozer_jacket_none_green"
                },
                {
                    "name": "None Pink",
                    "code": "sumi_net_pozer_jacket_none_pink"
                },
                {
                    "name": "None Purple",
                    "code": "sumi_net_pozer_jacket_none_purple"
                },
                {
                    "name": "None Red",
                    "code": "sumi_net_pozer_jacket_none_red"
                },
                {
                    "name": "None Yellow",
                    "code": "sumi_net_pozer_jacket_none_yellow"
                },
                {
                    "name": "Samurai Blue",
                    "code": "sumi_net_pozer_jacket_samurai_blue"
                },
                {
                    "name": "Samurai Green",
                    "code": "sumi_net_pozer_jacket_samurai_green"
                },
                {
                    "name": "Samurai Pink",
                    "code": "sumi_net_pozer_jacket_samurai_pink"
                },
                {
                    "name": "Samurai Purple",
                    "code": "sumi_net_pozer_jacket_samurai_purple"
                },
                {
                    "name": "Samurai Red",
                    "code": "sumi_net_pozer_jacket_samurai_red"
                },
                {
                    "name": "Samurai Yellow",
                    "code": "sumi_net_pozer_jacket_samurai_yellow"
                },
                {
                    "name": "Wolf Blue",
                    "code": "sumi_net_pozer_jacket_wolf_blue"
                },
                {
                    "name": "Wolf Green",
                    "code": "sumi_net_pozer_jacket_wolf_green"
                },
                {
                    "name": "Wolf Pink",
                    "code": "sumi_net_pozer_jacket_wolf_pink"
                },
                {
                    "name": "Wolf Purple",
                    "code": "sumi_net_pozer_jacket_wolf_purple"
                },
                {
                    "name": "Wolf Red",
                    "code": "sumi_net_pozer_jacket_wolf_red"
                },
                {
                    "name": "Wolf Yellow",
                    "code": "sumi_net_pozer_jacket_wolf_yellow"
                }
            ]
        }
    ]
}
