{
    "AXL": {
        "fullName": "ArchiveXL",
        "description": "Modder resource",
        "category": "Mods",
        "links": [
            {
                "label": "Nexus",
                "url": "https://www.nexusmods.com/cyberpunk2077/mods/4198"
            }
        ],
        "aliases": [
            "archivexl",
            "archive-xl"
        ]
    },
    "Accessories": {
        "description": "Clothing accessories",
        "category": "Clothing items",
        "aliases": [
            "accessory"
        ]
    },
    "Animated": {
        "description": "Animated clothing parts",
        "category": "Item properties",
        "aliases": [
            "animation"
        ]
    },
    "Arms": {
        "description": "Arms slot",
        "category": "Clothing slots",
        "aliases": [
            "arm"
        ]
    },
    "AutoScale": {
        "description": "Clothing that automatically scales to the player's level",
        "category": "Item properties",
        "aliases": [
            "autoscaling",
            "auto-scaling",
            "auto-scale",
            "auto-refit",
            "autorefit",
            "auto-refits"
        ]
    },
    "Belt": {
        "description": "Belt",
        "category": "Clothing items",
        "relatedTags": [
            "Waist"
        ],
        "aliases": [
            "belts"
        ]
    },
    "Body-Adonis": {
        "description": "Adonis: High-poly body with detailed musculature and definition",
        "category": "Mods - Body Mods - MaleV",
        "links": [
            {
                "label": "Nexus",
                "url": "https://www.nexusmods.com/cyberpunk2077/mods/4968"
            }
        ]
    },
    "Body-Atlas": {
        "description": "High poly body with hand-sculpted muscles",
        "category": "Mods - Body Mods - MaleV",
        "links": [
            {
                "label": "Nexus",
                "url": "https://www.nexusmods.com/cyberpunk2077/mods/8766"
            }
        ]
    },
    "Body-EVB": {
        "description": "Enhanced Vanilla Body; No refits needed",
        "category": "Mods - Body Mods - FemV",
        "links": [
            {
                "label": "Nexus",
                "url": "https://www.nexusmods.com/cyberpunk2077/mods/11489"
            }
        ]
    },
    "Body-Flat": {
        "description": "Flat chested body",
        "category": "Mods - Body Mods - FemV",
        "aliases": [
            "body-flat-chest",
            "flatbody",
            "body-nochest",
            "body-no-chest"
        ],
        "links": [
            {
                "label": "Nexus",
                "url": "https://www.nexusmods.com/cyberpunk2077/mods/6883"
            }
        ]
    },
    "Body-Gymfiend": {
        "description": "Muscular body",
        "category": "Mods - Body Mods - MaleV",
        "links": [
            {
                "label": "Nexus",
                "url": "https://www.nexusmods.com/cyberpunk2077/mods/6423"
            }
        ]
    },
    "Body-Hyst": {
        "description": "Enhanced Big Breasts, Realistic Butt, and more",
        "category": "Mods - Body Mods - FemV",
        "relatedTags": [
            "Body-Hyst-EBB",
            "Body-Hyst-RB",
            "Body-Hyst-EBBP",
            "Body-Hyst-EBBPRB",
            "Body-Hyst-EBBRB",
            "Body-Hyst-Angel"
        ],
        "links": [
            {
                "label": "Nexus",
                "url": "https://next.nexusmods.com/profile/LxRHyst/mods?gameId=3333"
            }
        ]
    },
    "Body-Hyst-Angel": {
        "description": "New improved version of the other Hyst body mods",
        "category": "Mods - Body Mods - FemV",
        "relatedTags": [
            "Body-Hyst-EBB",
            "Body-Hyst-RB",
            "Body-Hyst-EBBP"
        ],
        "links": [
            {
                "label": "Nexus",
                "url": "https://www.nexusmods.com/cyberpunk2077/mods/14896"
            }
        ],
        "aliases": [
            "body-angel"
        ]
    },
    "Body-Hyst-EBB": {
        "description": "EBB - Enhanced Big Breasts",
        "category": "Mods - Body Mods - FemV",
        "relatedTags": [
            "Body-Hyst-EBBRB",
            "Body-Hyst-EBBP",
            "Body-Hyst-EBBPRB",
            "Body-Hyst-EBBN"
        ],
        "links": [
            {
                "label": "Nexus",
                "url": "https://www.nexusmods.com/cyberpunk2077/mods/4654"
            }
        ],
        "aliases": [
            "body-ebb"
        ]
    },
    "Body-Hyst-EBBN": {
        "description": "Enhanced Big Breasts Natural",
        "category": "Mods - Body Mods - FemV",
        "relatedTags": [
            "Body-Hyst-EBBNRB"
        ],
        "aliases": [
            "body-ebbn"
        ],
        "links": [
            {
                "label": "Nexus",
                "url": "https://www.nexusmods.com/cyberpunk2077/mods/4654"
            }
        ]
    },
    "Body-Hyst-EBBNRB": {
        "description": "Enhanced Big Breasts Natural and Realistic Butt",
        "category": "Mods - Body Mods - FemV",
        "relatedTags": [
            "Body-Hyst-EBBN"
        ],
        "aliases": [
            "body-ebbnrb"
        ],
        "links": [
            {
                "label": "Nexus",
                "url": "https://www.nexusmods.com/cyberpunk2077/mods/4654"
            }
        ]
    },
    "Body-Hyst-EBBP": {
        "description": "EBBP - Enhanced Big Breasts and Push-Up",
        "category": "Mods - Body Mods - FemV",
        "relatedTags": [
            "Body-Hyst-EBB"
        ],
        "links": [
            {
                "label": "Nexus",
                "url": "https://www.nexusmods.com/cyberpunk2077/mods/9083"
            }
        ],
        "aliases": [
            "body-ebbp"
        ]
    },
    "Body-Hyst-EBBPRB": {
        "description": "EBBPRB - Enhanced Big Breasts, Push-Up and Realistic Butt",
        "category": "Mods - Body Mods - FemV",
        "relatedTags": [
            "Body-Hyst-EBBP",
            "Body-Hyst-RB"
        ],
        "links": [
            {
                "label": "Nexus",
                "url": "https://www.nexusmods.com/cyberpunk2077/mods/9083"
            }
        ],
        "aliases": [
            "body-ebbprb"
        ]
    },
    "Body-Hyst-EBBRB": {
        "description": "EBBRB - Enhanced Big Breasts and Realistic Butt",
        "category": "Mods - Body Mods - FemV",
        "relatedTags": [
            "Body-Hyst-EBB",
            "Body-Hyst-RB"
        ],
        "links": [
            {
                "label": "Nexus",
                "url": "https://www.nexusmods.com/cyberpunk2077/mods/4654"
            }
        ],
        "aliases": [
            "body-ebbrb",
            "body-hyst-ebb-bb",
            "body-hyst-ebb-rb"
        ]
    },
    "Body-Hyst-RB": {
        "description": "Realistic Butt body",
        "category": "Mods - Body Mods - FemV",
        "links": [
            {
                "label": "Nexus",
                "url": "https://www.nexusmods.com/cyberpunk2077/mods/4420"
            }
        ],
        "aliases": [
            "body-rb"
        ]
    },
    "Body-Lush": {
        "description": "Voluptuous body and large breasts",
        "category": "Mods - Body Mods - FemV",
        "relatedTags": [
            "Body-SoLush"
        ],
        "aliases": [
            "body-lush-large"
        ],
        "links": [
            {
                "label": "Nexus",
                "url": "https://www.nexusmods.com/cyberpunk2077/mods/4901"
            }
        ]
    },
    "Body-SoLush": {
        "description": "Lush body with more muscles",
        "category": "Mods - Body Mods - FemV",
        "relatedTags": [
            "Body-Lush"
        ],
        "links": [
            {
                "label": "Nexus",
                "url": "https://www.nexusmods.com/cyberpunk2077/mods/8392"
            }
        ]
    },
    "Body-Solo": {
        "description": "Rock-hard abs and toned body",
        "category": "Mods - Body Mods - FemV",
        "relatedTags": [
            "Body-Solo-Arms",
            "Body-Solo-Small",
            "Body-Solo-Ultimate"
        ],
        "links": [
            {
                "label": "Nexus",
                "url": "https://www.nexusmods.com/cyberpunk2077/mods/4813"
            }
        ]
    },
    "Body-Solo-Arms": {
        "description": "Athletic arms",
        "category": "Mods - Body Mods - FemV",
        "relatedTags": [
            "Body-Solo",
            "Body-Solo-Small",
            "Body-Solo-Ultimate"
        ],
        "links": [
            {
                "label": "Nexus",
                "url": "https://www.nexusmods.com/cyberpunk2077/mods/7148"
            }
        ],
        "aliases": [
            "body-soloarms"
        ]
    },
    "Body-Solo-Small": {
        "description": "Solo with small breasts",
        "category": "Mods - Body Mods - FemV",
        "links": [
            {
                "label": "Nexus",
                "url": "https://www.nexusmods.com/cyberpunk2077/mods/6213"
            }
        ],
        "aliases": [
            "body-small",
            "body-solo-small-breast"
        ]
    },
    "Body-Solo-Ultimate": {
        "description": "Solo with bigger breasts and butt",
        "category": "Mods - Body Mods - FemV",
        "relatedTags": [
            "Body-Solo",
            "Body-Solo-Small"
        ],
        "links": [
            {
                "label": "Nexus",
                "url": "https://www.nexusmods.com/cyberpunk2077/mods/6944"
            }
        ]
    },
    "Body-Songbird": {
        "description": "Songbird's body for the FemV player character",
        "category": "Mods - Body Mods - FemV",
        "links": [
            {
                "label": "Nexus",
                "url": "https://www.nexusmods.com/cyberpunk2077/mods/12898"
            }
        ]
    },
    "Body-Spawn0": {
        "description": "Body with a large choice of sizes and CET in-game body swap",
        "category": "Mods - Body Mods - FemV",
        "links": [
            {
                "label": "Nexus",
                "url": "https://www.nexusmods.com/cyberpunk2077/mods/1424"
            }
        ]
    },
    "Body-Valentine": {
        "description": "Body with improved proportions",
        "category": "Mods - Body Mods - FemV",
        "links": [
            {
                "label": "Nexus",
                "url": "https://www.nexusmods.com/cyberpunk2077/mods/4256"
            }
        ]
    },
    "Body-Vanilla": {
        "description": "The vanilla body for FemV and MaleV",
        "category": "Item properties"
    },
    "Body-VTK-Big": {
        "description": "Vanilla HD body with bigger breasts",
        "category": "Mods - Body Mods - FemV",
        "relatedTags": [
            "Body-VTK-Small",
            "Body-VTK-VanillaHD"
        ],
        "links": [
            {
                "label": "Nexus",
                "url": "https://www.nexusmods.com/cyberpunk2077/mods/7482"
            }
        ],
        "aliases": [
            "body-vanillahd-big",
            "body-vanilla-vtk-big"
        ]
    },
    "Body-VTK-Small": {
        "description": "Vanilla HD body with small breasts",
        "category": "Mods - Body Mods - FemV",
        "relatedTags": [
            "Body-VTK-Big",
            "Body-VTK-VanillaHD"
        ],
        "links": [
            {
                "label": "Nexus",
                "url": "https://www.nexusmods.com/cyberpunk2077/mods/7482"
            }
        ],
        "aliases": [
            "body-vanillahd-small",
            "body-vanilla-vtk-small"
        ]
    },
    "Body-VTK-VanillaHD": {
        "description": "High quality body, requires no refits",
        "category": "Mods - Body Mods - FemV",
        "links": [
            {
                "label": "Nexus",
                "url": "https://www.nexusmods.com/cyberpunk2077/mods/7054"
            }
        ],
        "aliases": [
            "body-vtk",
            "body-vanilla-hd",
            "body-vanillahd",
            "body-vtk-hd",
            "body-vtk-vanilla-hd"
        ]
    },
    "Bodysuit": {
        "description": "Bodysuit",
        "category": "Clothing items",
        "relatedTags": [
            "FullBody"
        ],
        "aliases": [
            "body-suit",
            "bodysuits"
        ]
    },
    "Boots": {
        "description": "Boots",
        "category": "Clothing items",
        "relatedTags": [
            "Feet"
        ],
        "aliases": [
            "boot"
        ]
    },
    "Bra": {
        "description": "Bra or bra-like",
        "category": "Clothing items",
        "relatedTags": [
            "Torso"
        ],
        "aliases": [
            "bras"
        ]
    },
    "CET": {
        "fullName": "Cyber Engine Tweaks",
        "description": "Modder resource",
        "category": "Mods",
        "links": [
            {
                "label": "Nexus",
                "url": "https://www.nexusmods.com/cyberpunk2077/mods/107"
            }
        ],
        "aliases": [
            "cyberenginetweaks",
            "cyber-engine-tweaks"
        ]
    },
    "CDW": {
        "fullName": "Codeware",
        "description": "Modder resource",
        "category": "Mods",
        "links": [
            {
                "label": "Nexus",
                "url": "https://www.nexusmods.com/cyberpunk2077/mods/7780"
            }
        ],
        "aliases": [
            "codeware",
            "code-ware"
        ]
    },
    "Choker": {
        "description": "Neck choker",
        "category": "Clothing items",
        "relatedTags": [
            "Neck"
        ],
        "aliases": [
            "chokers",
            "collar"
        ]
    },
    "Clothing": {
        "description": "Clothing items",
        "category": "Item properties"
    },
    "Coat": {
        "description": "Coat",
        "category": "Clothing items",
        "relatedTags": [
            "FullBody"
        ],
        "aliases": [
            "coats"
        ]
    },
    "Decals": {
        "description": "Decals or stickers to use on clothing items",
        "category": "Clothing items",
        "aliases": [
            "decal",
            "stickers",
            "sticker"
        ]
    },
    "DIY": {
        "fullName": "Do-It-Yourself",
        "description": "Clothing items that can be customized with Wolvenkit",
        "category": "Item properties",
        "aliases": [
            "doityourself",
            "do-it-yourself"
        ]
    },
    "Dress": {
        "description": "Dress",
        "category": "Clothing items",
        "relatedTags": [
            "FullBody"
        ],
        "aliases": [
            "dresses"
        ]
    },
    "Earring": {
        "description": "Earring",
        "category": "Clothing items",
        "relatedTags": [
            "Head"
        ],
        "aliases": [
            "earrings"
        ]
    },
    "EQEX": {
        "fullName": "Equipment-EX",
        "description": "Layering of clothing items",
        "category": "Mods",
        "links": [
            {
                "label": "Nexus",
                "url": "https://www.nexusmods.com/cyberpunk2077/mods/6945"
            }
        ],
        "aliases": [
            "equipmentex",
            "equipment-ex"
        ]
    },
    "Emissive": {
        "description": "Clothing items that glow or emit light in some way",
        "category": "Item properties",
        "aliases": [
            "glow"
        ]
    },
    "Feet": {
        "description": "Feet slot",
        "category": "Clothing slots",
        "aliases": [
            "foot"
        ]
    },
    "FemV": {
        "description": "Items restricted to female V characters",
        "category": "Item properties"
    },
    "FullBody": {
        "description": "Full body clothing items",
        "category": "Clothing slots",
        "aliases": [
            "fullbody",
            "full-body"
        ]
    },
    "GarmentSupport": {
        "description": "Clothing system that handles tucking pants into boots and shirts under jackets.",
        "category": "Item properties",
        "links": [
            {
                "label": "Modding Wiki article",
                "url": "https://wiki.redmodding.org/cyberpunk-2077-modding/for-mod-creators-theory/3d-modelling/garment-support-how-does-it-work"
            }
        ],
        "aliases": [
            "garmentssupport",
            "garment-support",
            "garments-support"
        ]
    },
    "Glasses": {
        "description": "Glasses",
        "category": "Clothing items",
        "relatedTags": [
            "Head"
        ]
    },
    "Gloves": {
        "description": "Gloves",
        "category": "Clothing items",
        "relatedTags": [
            "Hands"
        ],
        "aliases": [
            "glove"
        ]
    },
    "Hair": {
        "description": "Hair slot",
        "category": "Clothing slots"
    },
    "Hands": {
        "description": "Hand slot",
        "category": "Clothing slots",
        "aliases": [
            "hand"
        ]
    },
    "Hat": {
        "description": "Hat",
        "category": "Clothing items",
        "relatedTags": [
            "Head"
        ],
        "aliases": [
            "hats"
        ]
    },
    "Head": {
        "description": "Head slot",
        "category": "Clothing slots",
        "aliases": [
            "headgear",
            "face"
        ]
    },
    "Holo": {
        "description": "Holographic items",
        "category": "Item properties",
        "aliases": [
            "hologram",
            "holograms",
            "holographic"
        ]
    },
    "Jacket": {
        "description": "Jacket, Blazer, Bolero",
        "category": "Clothing items",
        "relatedTags": [
            "Torso"
        ],
        "aliases": [
            "jackets",
            "blazer",
            "blazers",
            "bolero",
            "boleros"
        ]
    },
    "Jewelry": {
        "description": "Jewelry",
        "category": "Clothing items",
        "aliases": [
            "jewellery",
            "jewlery",
            "jewelery"
        ]
    },
    "Leggings": {
        "description": "Leggings, stretch pants",
        "category": "Clothing items",
        "relatedTags": [
            "Legs"
        ],
        "aliases": [
            "legging",
            "stretchpants",
            "stretchpant",
            "stretch-pants",
            "stretch-pant"
        ]
    },
    "Legs": {
        "description": "Leg slot",
        "category": "Clothing slots",
        "aliases": [
            "leg"
        ]
    },
    "MaleV": {
        "description": "Items restricted to male V characters",
        "category": "Item properties"
    },
    "Mask": {
        "description": "Mask",
        "category": "Clothing items",
        "relatedTags": [
            "Head"
        ],
        "aliases": [
            "masks"
        ]
    },
    "Modular": {
        "description": "Modular clothing items that can be combined in different ways",
        "category": "Item properties"
    },
    "Navel": {
        "description": "Navel slot",
        "category": "Clothing slots"
    },
    "Neck": {
        "description": "Neck slot",
        "category": "Clothing slots"
    },
    "Necklace": {
        "description": "Necklace",
        "category": "Clothing items",
        "relatedTags": [
            "Neck"
        ],
        "aliases": [
            "necklaces"
        ]
    },
    "Outfit": {
        "description": "Set of clothing items for a full-themed outfit",
        "category": "Item properties",
        "aliases": [
            "outfits"
        ]
    },
    "Panties": {
        "description": "Panties",
        "category": "Clothing items",
        "relatedTags": [
            "Legs"
        ],
        "aliases": [
            "panty"
        ]
    },
    "Pants": {
        "description": "Pants",
        "category": "Clothing items",
        "relatedTags": [
            "Legs"
        ],
        "aliases": [
            "jeans"
        ]
    },
    "Physics": {
        "description": "Items with working physics",
        "category": "Item properties"
    },
    "Piercing": {
        "description": "Piercing",
        "category": "Clothing items",
        "aliases": [
            "piercings"
        ]
    },
    "R4EX": {
        "fullName": "Red4Ext",
        "description": "Modder resource",
        "category": "Mods",
        "links": [
            {
                "label": "Nexus",
                "url": "https://www.nexusmods.com/cyberpunk2077/mods/2380"
            }
        ],
        "aliases": [
            "red4ext",
            "red-4-ext",
            "red4",
            "red-4",
            "redx"
        ]
    },
    "Reflective": {
        "description": "Items with reflective surfaces",
        "category": "Item properties",
        "aliases": [
            "reflect",
            "reflection",
            "chrome",
            "chrom",
            "chromed",
            "chromatic",
            "reflections"
        ]
    },
    "Ring": {
        "description": "Ring",
        "category": "Clothing items",
        "relatedTags": [
            "Hands"
        ],
        "aliases": [
            "rings"
        ]
    },
    "Shirt": {
        "description": "Shirt",
        "category": "Clothing items",
        "relatedTags": [
            "Torso"
        ],
        "aliases": [
            "shirts",
            "t-shirt",
            "t-shirts",
            "tshirt",
            "tshirts"
        ]
    },
    "Shoes": {
        "description": "Shoes",
        "category": "Clothing items",
        "relatedTags": [
            "Feet"
        ],
        "aliases": [
            "shoe"
        ]
    },
    "Shorts": {
        "description": "Shorts",
        "category": "Clothing items",
        "relatedTags": [
            "Legs"
        ]
    },
    "Skimpy": {
        "description": "Clothing items that are revealing",
        "category": "Item properties",
        "aliases": [
            "sexy",
            "nude",
            "nudity",
            "nsfw"
        ]
    },
    "Skirt": {
        "description": "Skirt",
        "category": "Clothing items",
        "relatedTags": [
            "Legs"
        ],
        "aliases": [
            "skirts"
        ]
    },
    "Sleeves": {
        "description": "Sleeves",
        "category": "Clothing items",
        "relatedTags": [
            "Arms"
        ],
        "aliases": [
            "sleeve"
        ]
    },
    "Stockings": {
        "description": "Stockings",
        "category": "Clothing items",
        "relatedTags": [
            "Legs"
        ]
    },
    "Suit": {
        "description": "Suit",
        "category": "Clothing items",
        "relatedTags": [
            "FullBody"
        ],
        "aliases": [
            "suits"
        ]
    },
    "TXL": {
        "fullName": "Tweak XL",
        "description": "Tweak XL: Modder resource",
        "category": "Mods",
        "links": [
            {
                "label": "Nexus",
                "url": "https://www.nexusmods.com/cyberpunk2077/mods/4197"
            }
        ],
        "aliases": [
            "tweakxl",
            "tweak-xl"
        ]
    },
    "Top": {
        "description": "Top",
        "category": "Clothing items",
        "relatedTags": [
            "Torso"
        ],
        "aliases": [
            "tops"
        ]
    },
    "Torso": {
        "description": "Torso slot",
        "category": "Clothing slots"
    },
    "Transparent": {
        "description": "Items with transparency",
        "category": "Item properties",
        "aliases": [
            "translucent",
            "transparencies",
            "transparency",
            "see-through",
            "seethrough",
            "see-thru",
            "seethru"
        ]
    },
    "Underwear": {
        "description": "Underwear",
        "category": "Clothing items",
        "relatedTags": [
            "Skimpy"
        ],
        "aliases": [
            "undergarment",
            "undergarments"
        ]
    },
    "VAT": {
        "fullName": "Virtual Atelier",
        "description": "Adds clothing stores to the in-game browser.",
        "category": "Mods",
        "links": [
            {
                "label": "Nexus",
                "url": "https://www.nexusmods.com/cyberpunk2077/mods/2987"
            }
        ],
        "aliases": [
            "virtual-atelier",
            "virtualatelier",
            "atelier",
            "vat",
            "va"
        ]
    },
    "Waist": {
        "description": "Waist slot",
        "category": "Clothing slots"
    }
}
